fastgif.py
fastgif-1.1.dist-info/LICENSE
fastgif-1.1.dist-info/METADATA
fastgif-1.1.dist-info/WHEEL
fastgif-1.1.dist-info/top_level.txt
fastgif-1.1.dist-info/RECORD
