Metadata-Version: 2.1
Name: fastgif
Version: 1.1
Summary: Matplotlib GIF maker
Home-page: https://github.com/matejmurin01/fastgif
Author: Matej Murín
Author-email: matejmurin01@gmail.com
License: Apache License 2.0
Keywords: gif,gifs,animation,matplotlib
Requires-Python: >=3.8.12
License-File: LICENSE
Requires-Dist: matplotlib (>=3.5.0)
Requires-Dist: imageio (>=2.9.0)
